bert_text_pretty/__init__.py
bert_text_pretty/test_py.py
bert_text_pretty/tokenization.py
bert_text_pretty/cls/__init__.py
bert_text_pretty/cls/utils.py
bert_text_pretty/ner/__init__.py
bert_text_pretty/ner/utils.py
bert_text_pretty/relation/__init__.py
bert_text_pretty/relation/utils.py
bert_text_pretty-0.0.18.dist-info/METADATA
bert_text_pretty-0.0.18.dist-info/WHEEL
bert_text_pretty-0.0.18.dist-info/top_level.txt
bert_text_pretty-0.0.18.dist-info/RECORD
