Metadata-Version: 2.1
Name: bert-text-pretty
Version: 0.0.18
Summary: bert_text_pretty 是一个bert 文本特征化和文本后处理解码的包，用于bert工程推理
Home-page: https://github.com/ssbuild/bert_text_pretty
Author: ssbuild
Author-email: 9727464@qq.com
License: Apache 2.0
Keywords: bert_text_pretty,bert_text_pretty,bert text pretty,bert decording
Platform: win32_AMD64
Classifier: Development Status :: 5 - Production/Stable
Classifier: Intended Audience :: Developers
Classifier: Intended Audience :: Education
Classifier: Intended Audience :: Science/Research
Classifier: License :: OSI Approved :: Apache Software License
Classifier: Programming Language :: C++
Classifier: Programming Language :: Python :: 3
Classifier: Programming Language :: Python :: 3.6
Classifier: Programming Language :: Python :: 3.7
Classifier: Programming Language :: Python :: 3.8
Classifier: Programming Language :: Python :: 3.9
Classifier: Topic :: Scientific/Engineering
Classifier: Topic :: Scientific/Engineering :: Mathematics
Classifier: Topic :: Scientific/Engineering :: Artificial Intelligence
Classifier: Topic :: Software Development
Classifier: Topic :: Software Development :: Libraries
Classifier: Topic :: Software Development :: Libraries :: Python Modules
Requires-Python: >=3, <4
